discrete_probabilistic_model/__init__.py
discrete_probabilistic_model/discrete_probabilistic_model.py
discrete_probabilistic_model/prob_model.py
discrete_probabilistic_model/utils.py
discrete_probabilistic_model-0.1.1.dist-info/AUTHORS.rst
discrete_probabilistic_model-0.1.1.dist-info/LICENSE
discrete_probabilistic_model-0.1.1.dist-info/METADATA
discrete_probabilistic_model-0.1.1.dist-info/WHEEL
discrete_probabilistic_model-0.1.1.dist-info/top_level.txt
discrete_probabilistic_model-0.1.1.dist-info/RECORD
