Metadata-Version: 2.1
Name: discrete-probabilistic-model
Version: 0.1.1
Summary: A simple probabilistic modeling framework with discrete variables.
Home-page: https://github.com/andrewnam/discrete_probabilistic_model
Author: Andrew Nam
Author-email: andrewnam95@gmail.com
License: MIT license
Keywords: discrete_probabilistic_model
Classifier: Development Status :: 2 - Pre-Alpha
Classifier: Intended Audience :: Developers
Classifier: License :: OSI Approved :: MIT License
Classifier: Natural Language :: English
Classifier: Programming Language :: Python :: 3
Classifier: Programming Language :: Python :: 3.6
Classifier: Programming Language :: Python :: 3.7
Classifier: Programming Language :: Python :: 3.8
Requires-Python: >=3.6
License-File: LICENSE
License-File: AUTHORS.rst
Requires-Dist: numpy
Requires-Dist: frozendict
